mackerel/__init__.py
mackerel/build.py
mackerel/cli.py
mackerel/config.py
mackerel/parsers.py
mackerel/renderers.py
mackerel/types.py
mackerel/site/mackerelconfig.toml
mackerel/site/content/about.md
mackerel/site/content/index.md
mackerel/site/content/img/logo.svg
mackerel/site/content/posts/hello-world.md
mackerel/site/content/posts/index.md
mackerel/site/content/posts/second.md
mackerel/site/templates/starter/base.html
mackerel/site/templates/starter/footer.html
mackerel/site/templates/starter/header.html
mackerel/site/templates/starter/home.html
mackerel/site/templates/starter/list.html
mackerel/site/templates/starter/nav.html
mackerel/site/templates/starter/page.html
mackerel/site/templates/starter/assets/favicon.ico
mackerel-0.3.0.dist-info/METADATA
mackerel-0.3.0.dist-info/WHEEL
mackerel-0.3.0.dist-info/entry_points.txt
mackerel-0.3.0.dist-info/licenses/LICENSE
mackerel-0.3.0.dist-info/RECORD
