Metadata-Version: 2.4
Name: mackerel
Version: 0.3.0
Summary: Minimal static site generator built with type annotations
Project-URL: Homepage, https://mackerel.sh
Project-URL: Repository, https://github.com/pkolios/mackerel
Project-URL: Changelog, https://github.com/pkolios/mackerel/blob/main/CHANGELOG.md
Author-email: Paris Kolios <hey@pariskolios.com>
License-Expression: MIT
License-File: LICENSE
Keywords: cli,markdown,static site generator,type annotations
Classifier: Development Status :: 2 - Pre-Alpha
Classifier: Environment :: Console
Classifier: Environment :: Web Environment
Classifier: Intended Audience :: Developers
Classifier: Intended Audience :: End Users/Desktop
Classifier: License :: OSI Approved :: MIT License
Classifier: Operating System :: OS Independent
Classifier: Programming Language :: Python
Classifier: Programming Language :: Python :: 3
Classifier: Programming Language :: Python :: 3 :: Only
Classifier: Programming Language :: Python :: 3.11
Classifier: Topic :: Documentation
Classifier: Topic :: Internet :: WWW/HTTP :: Dynamic Content
Classifier: Topic :: Internet :: WWW/HTTP :: Dynamic Content :: Content Management System
Classifier: Topic :: Software Development :: Documentation
Classifier: Topic :: Text Processing :: Markup :: HTML
Requires-Python: >=3.11
Requires-Dist: click
Requires-Dist: jinja2
Requires-Dist: markdown
Requires-Dist: python-dateutil>=2.9.0.post0
Requires-Dist: python-frontmatter>=1.1.0
Requires-Dist: tomli-w>=1.2.0
Requires-Dist: watchfiles>=1.1.0
